{"result_num": 26, "result": [{"p1": {"x": 192, "y": 162}, "p2": {"x": 192, "y": 217}, "thickness": 1}, {"p1": {"x": 119, "y": 217}, "p2": {"x": 192, "y": 217}, "thickness": 1}, {"p1": {"x": 416, "y": 314}, "p2": {"x": 416, "y": 570}, "thickness": 1}, {"p1": {"x": 253, "y": 570}, "p2": {"x": 416, "y": 570}, "thickness": 1}, {"p1": {"x": 120, "y": 570}, "p2": {"x": 253, "y": 570}, "thickness": 1}, {"p1": {"x": 120, "y": 391}, "p2": {"x": 120, "y": 570}, "thickness": 1}, {"p1": {"x": 119, "y": 315}, "p2": {"x": 148, "y": 315}, "thickness": 1}, {"p1": {"x": 119, "y": 217}, "p2": {"x": 119, "y": 315}, "thickness": 1}, {"p1": {"x": 119, "y": 79}, "p2": {"x": 119, "y": 217}, "thickness": 1}, {"p1": {"x": 119, "y": 79}, "p2": {"x": 192, "y": 79}, "thickness": 1}, {"p1": {"x": 120, "y": 391}, "p2": {"x": 148, "y": 391}, "thickness": 1}, {"p1": {"x": 148, "y": 315}, "p2": {"x": 188, "y": 315}, "thickness": 1}, {"p1": {"x": 188, "y": 315}, "p2": {"x": 188, "y": 389}, "thickness": 1}, {"p1": {"x": 253, "y": 78}, "p2": {"x": 416, "y": 78}, "thickness": 1}, {"p1": {"x": 416, "y": 78}, "p2": {"x": 416, "y": 314}, "thickness": 1}, {"p1": {"x": 148, "y": 315}, "p2": {"x": 148, "y": 389}, "thickness": 1}, {"p1": {"x": 192, "y": 78}, "p2": {"x": 253, "y": 78}, "thickness": 1}, {"p1": {"x": 192, "y": 78}, "p2": {"x": 192, "y": 162}, "thickness": 1}, {"p1": {"x": 253, "y": 78}, "p2": {"x": 253, "y": 162}, "thickness": 1}, {"p1": {"x": 253, "y": 162}, "p2": {"x": 253, "y": 314}, "thickness": 1}, {"p1": {"x": 192, "y": 162}, "p2": {"x": 253, "y": 162}, "thickness": 1}, {"p1": {"x": 253, "y": 314}, "p2": {"x": 253, "y": 389}, "thickness": 1}, {"p1": {"x": 253, "y": 389}, "p2": {"x": 253, "y": 570}, "thickness": 1}, {"p1": {"x": 188, "y": 389}, "p2": {"x": 253, "y": 389}, "thickness": 1}, {"p1": {"x": 253, "y": 314}, "p2": {"x": 416, "y": 314}, "thickness": 1}, {"p1": {"x": 148, "y": 389}, "p2": {"x": 188, "y": 389}, "thickness": 1}]}