{"result_num": 21, "result": [{"p1": {"x": 289, "y": 212}, "p2": {"x": 289, "y": 295}, "thickness": 1}, {"p1": {"x": 142, "y": 295}, "p2": {"x": 289, "y": 295}, "thickness": 1}, {"p1": {"x": 345, "y": 314}, "p2": {"x": 345, "y": 343}, "thickness": 1}, {"p1": {"x": 291, "y": 343}, "p2": {"x": 345, "y": 343}, "thickness": 1}, {"p1": {"x": 413, "y": 314}, "p2": {"x": 413, "y": 546}, "thickness": 1}, {"p1": {"x": 291, "y": 546}, "p2": {"x": 413, "y": 546}, "thickness": 1}, {"p1": {"x": 291, "y": 495}, "p2": {"x": 291, "y": 546}, "thickness": 1}, {"p1": {"x": 142, "y": 495}, "p2": {"x": 291, "y": 495}, "thickness": 1}, {"p1": {"x": 142, "y": 295}, "p2": {"x": 142, "y": 495}, "thickness": 1}, {"p1": {"x": 83, "y": 212}, "p2": {"x": 142, "y": 212}, "thickness": 1}, {"p1": {"x": 83, "y": 66}, "p2": {"x": 83, "y": 212}, "thickness": 1}, {"p1": {"x": 345, "y": 213}, "p2": {"x": 345, "y": 314}, "thickness": 1}, {"p1": {"x": 345, "y": 213}, "p2": {"x": 357, "y": 213}, "thickness": 1}, {"p1": {"x": 291, "y": 343}, "p2": {"x": 291, "y": 495}, "thickness": 1}, {"p1": {"x": 83, "y": 66}, "p2": {"x": 357, "y": 66}, "thickness": 1}, {"p1": {"x": 357, "y": 66}, "p2": {"x": 357, "y": 213}, "thickness": 1}, {"p1": {"x": 142, "y": 212}, "p2": {"x": 289, "y": 212}, "thickness": 1}, {"p1": {"x": 357, "y": 213}, "p2": {"x": 413, "y": 213}, "thickness": 1}, {"p1": {"x": 413, "y": 213}, "p2": {"x": 413, "y": 314}, "thickness": 1}, {"p1": {"x": 142, "y": 212}, "p2": {"x": 142, "y": 295}, "thickness": 1}, {"p1": {"x": 345, "y": 314}, "p2": {"x": 413, "y": 314}, "thickness": 1}]}