{"result_num": 22, "result": [{"p1": {"x": 142, "y": 283}, "p2": {"x": 222, "y": 283}, "thickness": 1}, {"p1": {"x": 431, "y": 403}, "p2": {"x": 431, "y": 536}, "thickness": 1}, {"p1": {"x": 218, "y": 536}, "p2": {"x": 431, "y": 536}, "thickness": 1}, {"p1": {"x": 143, "y": 403}, "p2": {"x": 218, "y": 403}, "thickness": 1}, {"p1": {"x": 143, "y": 327}, "p2": {"x": 143, "y": 403}, "thickness": 1}, {"p1": {"x": 218, "y": 403}, "p2": {"x": 218, "y": 536}, "thickness": 1}, {"p1": {"x": 81, "y": 134}, "p2": {"x": 142, "y": 134}, "thickness": 1}, {"p1": {"x": 81, "y": 69}, "p2": {"x": 81, "y": 134}, "thickness": 1}, {"p1": {"x": 264, "y": 283}, "p2": {"x": 264, "y": 403}, "thickness": 1}, {"p1": {"x": 264, "y": 283}, "p2": {"x": 432, "y": 283}, "thickness": 1}, {"p1": {"x": 81, "y": 69}, "p2": {"x": 295, "y": 69}, "thickness": 1}, {"p1": {"x": 295, "y": 69}, "p2": {"x": 295, "y": 133}, "thickness": 1}, {"p1": {"x": 295, "y": 133}, "p2": {"x": 432, "y": 133}, "thickness": 1}, {"p1": {"x": 432, "y": 133}, "p2": {"x": 432, "y": 283}, "thickness": 1}, {"p1": {"x": 142, "y": 327}, "p2": {"x": 218, "y": 327}, "thickness": 1}, {"p1": {"x": 218, "y": 327}, "p2": {"x": 218, "y": 403}, "thickness": 1}, {"p1": {"x": 142, "y": 133}, "p2": {"x": 295, "y": 133}, "thickness": 1}, {"p1": {"x": 142, "y": 133}, "p2": {"x": 142, "y": 283}, "thickness": 1}, {"p1": {"x": 432, "y": 283}, "p2": {"x": 432, "y": 403}, "thickness": 1}, {"p1": {"x": 264, "y": 403}, "p2": {"x": 432, "y": 403}, "thickness": 1}, {"p1": {"x": 218, "y": 403}, "p2": {"x": 264, "y": 403}, "thickness": 1}, {"p1": {"x": 142, "y": 283}, "p2": {"x": 142, "y": 327}, "thickness": 1}]}