{"result_num": 29, "result": [{"p1": {"x": 190, "y": 118}, "p2": {"x": 190, "y": 172}, "thickness": 1}, {"p1": {"x": 162, "y": 172}, "p2": {"x": 190, "y": 172}, "thickness": 1}, {"p1": {"x": 353, "y": 390}, "p2": {"x": 353, "y": 545}, "thickness": 1}, {"p1": {"x": 281, "y": 545}, "p2": {"x": 353, "y": 545}, "thickness": 1}, {"p1": {"x": 249, "y": 545}, "p2": {"x": 249, "y": 570}, "thickness": 1}, {"p1": {"x": 193, "y": 570}, "p2": {"x": 249, "y": 570}, "thickness": 1}, {"p1": {"x": 193, "y": 543}, "p2": {"x": 193, "y": 570}, "thickness": 1}, {"p1": {"x": 162, "y": 543}, "p2": {"x": 193, "y": 543}, "thickness": 1}, {"p1": {"x": 162, "y": 390}, "p2": {"x": 162, "y": 543}, "thickness": 1}, {"p1": {"x": 260, "y": 175}, "p2": {"x": 353, "y": 175}, "thickness": 1}, {"p1": {"x": 260, "y": 118}, "p2": {"x": 260, "y": 175}, "thickness": 1}, {"p1": {"x": 249, "y": 545}, "p2": {"x": 281, "y": 545}, "thickness": 1}, {"p1": {"x": 162, "y": 172}, "p2": {"x": 162, "y": 321}, "thickness": 1}, {"p1": {"x": 190, "y": 118}, "p2": {"x": 260, "y": 118}, "thickness": 1}, {"p1": {"x": 305, "y": 56}, "p2": {"x": 353, "y": 56}, "thickness": 1}, {"p1": {"x": 353, "y": 56}, "p2": {"x": 353, "y": 175}, "thickness": 1}, {"p1": {"x": 260, "y": 14}, "p2": {"x": 305, "y": 14}, "thickness": 1}, {"p1": {"x": 305, "y": 14}, "p2": {"x": 305, "y": 56}, "thickness": 1}, {"p1": {"x": 281, "y": 390}, "p2": {"x": 353, "y": 390}, "thickness": 1}, {"p1": {"x": 281, "y": 390}, "p2": {"x": 281, "y": 545}, "thickness": 1}, {"p1": {"x": 238, "y": 390}, "p2": {"x": 281, "y": 390}, "thickness": 1}, {"p1": {"x": 353, "y": 175}, "p2": {"x": 353, "y": 390}, "thickness": 1}, {"p1": {"x": 260, "y": 56}, "p2": {"x": 260, "y": 118}, "thickness": 1}, {"p1": {"x": 260, "y": 56}, "p2": {"x": 305, "y": 56}, "thickness": 1}, {"p1": {"x": 238, "y": 321}, "p2": {"x": 238, "y": 390}, "thickness": 1}, {"p1": {"x": 162, "y": 390}, "p2": {"x": 238, "y": 390}, "thickness": 1}, {"p1": {"x": 162, "y": 321}, "p2": {"x": 238, "y": 321}, "thickness": 1}, {"p1": {"x": 162, "y": 321}, "p2": {"x": 162, "y": 390}, "thickness": 1}, {"p1": {"x": 260, "y": 14}, "p2": {"x": 260, "y": 56}, "thickness": 1}]}